README.rst
setup.cfg
setup.py
bin/mcman
mc_man.egg-info/PKG-INFO
mc_man.egg-info/SOURCES.txt
mc_man.egg-info/dependency_links.txt
mc_man.egg-info/requires.txt
mc_man.egg-info/top_level.txt
mcman/__init__.py
mcman/command.py
mcman/mcman.py
mcman/commands/__init__.py
mcman/commands/export.py
mcman/commands/import_cmd.py
mcman/commands/plugins.py
mcman/commands/servers.py
mcman/logic/__init__.py
mcman/logic/common.py
mcman/logic/servers.py
mcman/logic/plugins/__init__.py
mcman/logic/plugins/plugins.py
mcman/logic/plugins/utils.py