Metadata-Version: 1.1
Name: mc-man
Version: 0.9-1
Summary: The Minecraft server jar and plugin manager, downloader and updater
Home-page: https://github.com/CubeEngineDev/mc-man
Author: totokaka
Author-email: mail@totokaka.io
License: GPLv3+
Platform: UNKNOWN
Classifier: Development Status :: 4 - Beta
Classifier: Environment :: Console
Classifier: Intended Audience :: System Administrators
Classifier: License :: OSI Approved :: GNU General Public License v3 or later (GPLv3+)
Classifier: Natural Language :: English
Classifier: Operating System :: Unix
Classifier: Programming Language :: Python
Classifier: Programming Language :: Python :: 3
Classifier: Programming Language :: Python :: 3.3
Classifier: Programming Language :: Python :: 3.4
Classifier: Topic :: System :: Systems Administration
Classifier: Topic :: Utilities
